{
  "parent": "minecraft:item/generated",
  "textures": {
    "layer0": "stardewcraft:item/fish/smoked/gemfish",
    "particle": "stardewcraft:item/fish/smoked/gemfish"
  },
  "overrides": [
    {
      "predicate": {
        "custom_model_data": 1
      },
      "model": "stardewcraftsve:item/smoked_gemfish_base_silver"
    },
    {
      "predicate": {
        "custom_model_data": 2
      },
      "model": "stardewcraftsve:item/smoked_gemfish_base_gold"
    },
    {
      "predicate": {
        "custom_model_data": 3
      },
      "model": "stardewcraftsve:item/smoked_gemfish_base_iridium"
    }
  ]
}